mavcom/__init__.py
mavcom/mavconstants.py
mavcom/mavcontrol.py
mavcom/video.py
mavcon-1.1.3.dist-info/LICENSE
mavcon-1.1.3.dist-info/METADATA
mavcon-1.1.3.dist-info/WHEEL
mavcon-1.1.3.dist-info/entry_points.txt
mavcon-1.1.3.dist-info/top_level.txt
mavcon-1.1.3.dist-info/RECORD
