Metadata-Version: 2.1
Name: mavcon
Version: 1.1.3
Summary: A python package that provides simplified drone flight control
Author-email: Mavscient <mavscient@xee4c.33mail.com>
License: MIT License
Project-URL: Homepage, https://github.com/Mavscient/Mavcon
Keywords: mavlink,drone,drones,pymavlink,dronekit
Classifier: License :: OSI Approved :: MIT License
Classifier: Programming Language :: Python
Classifier: Programming Language :: Python :: 3
Requires-Python: >=3.9
License-File: LICENSE
Requires-Dist: pymavlink
Requires-Dist: pyserial
Provides-Extra: dev
Requires-Dist: black ; extra == 'dev'
Requires-Dist: pip-tools ; extra == 'dev'
Requires-Dist: pytest ; extra == 'dev'
